<!DOCTYPE ui:UiBinder SYSTEM "http://dl.google.com/gwt/DTD/xhtml.ent">
<ui:UiBinder xmlns:ui="urn:ui:com.google.gwt.uibinder"
             xmlns:g="urn:import:com.google.gwt.user.client.ui">

    <ui:with field="resources" type="com.gwtplatform.samples.tab.client.resources.AppResources"/>

    <g:HTMLPanel>
        <h2>Local dialog sample</h2>

        <p>Clicking on the
            <strong>Dialogs</strong>
            tab will always come back to the
            <strong>Global</strong>
            tab.
        </p>

        <p>
            <g:Button ui:field="localDialog">Launch local dialog</g:Button>
        </p>

        <p>
            Lorem ipsum dolor sit amet, consectetur adipisicing elit. Assumenda atque cupiditate est fugit nemo,
            provident qui recusandae sapiente unde! Autem impedit nihil placeat veritatis! Nam nostrum perferendis quas
            soluta vel!
        </p>

        <p>
            Lorem ipsum dolor sit amet, consectetur adipisicing elit. Atque et, maiores. Animi delectus earum facilis
            maiores odio porro, possimus quo similique veritatis vero. Adipisci amet enim odio, pariatur quas repellat?
            Lorem ipsum dolor sit amet, consectetur adipisicing elit. Alias amet blanditiis corporis doloremque error,
            et excepturi fugit illo illum, itaque labore modi mollitia, natus nihil quod sequi tenetur velit voluptatum.
        </p>

        <p>
            Lorem ipsum dolor sit amet, consectetur adipisicing elit. Atque et, maiores. Animi delectus earum facilis
            maiores odio porro, possimus quo similique veritatis vero. Adipisci amet enim odio, pariatur quas repellat?
            Lorem ipsum dolor sit amet, consectetur adipisicing elit. Alias amet blanditiis corporis doloremque error,
            et excepturi fugit illo illum, itaque labore modi mollitia, natus nihil quod sequi tenetur velit voluptatum.
        </p>

        <p>
            Lorem ipsum dolor sit amet, consectetur adipisicing elit. Atque et, maiores. Animi delectus earum facilis
            maiores odio porro, possimus quo similique veritatis vero. Adipisci amet enim odio, pariatur quas repellat?
            Lorem ipsum dolor sit amet, consectetur adipisicing elit. Alias amet blanditiis corporis doloremque error,
            et excepturi fugit illo illum, itaque labore modi mollitia, natus nihil quod sequi tenetur velit voluptatum.
        </p>
    </g:HTMLPanel>
</ui:UiBinder>
